LICENSE
MANIFEST.in
README.rst
requirements.txt
setup.py
pytgram/__init__.py
pytgram/api.py
pytgram/content.py
pytgram/inline.py
pytgram/markup.py
pytgram/url.py
pytgram/webhook.py
pytgram.egg-info/PKG-INFO
pytgram.egg-info/SOURCES.txt
pytgram.egg-info/dependency_links.txt
pytgram.egg-info/requires.txt
pytgram.egg-info/top_level.txt
tests/__init__.py
tests/test_api.py
tests/test_markup.py
tests/test_url.py
tests/test_webhook.py
tests/files/python.png
tests/files/python2.png
tests/files/test.mp3
tests/files/test.mp4
tests/files/test.ogg
tests/files/test.pdf
tests/files/test.webp